Bono2SDGC/__init__.py
Bono2SDGC/modulo1.py
Bono2SDGC/modulo2.py
Bono2SDGC-0.1.3.dist-info/METADATA
Bono2SDGC-0.1.3.dist-info/WHEEL
Bono2SDGC-0.1.3.dist-info/top_level.txt
Bono2SDGC-0.1.3.dist-info/RECORD
