Metadata-Version: 2.1
Name: Bono2SDGC
Version: 0.1.3
Summary: Bono2
Home-page: https://gitlab.com/sebasdgc14/personal
Author: Sebastian Diaz Granados Cano
Author-email: sebasdgc14@gmail.com
License: MIT
Requires-Python: >=3.10.12
Requires-Dist: matplotlib ==3.8.1
Requires-Dist: pandas ==2.1.2
Requires-Dist: numpy ==1.26.1
